querytree/__init__.py
querytree-0.1.1.dist-info/LICENSE.txt
querytree-0.1.1.dist-info/METADATA
querytree-0.1.1.dist-info/WHEEL
querytree-0.1.1.dist-info/top_level.txt
querytree-0.1.1.dist-info/RECORD
