Metadata-Version: 2.1
Name: querytree
Version: 0.1.1
Summary: A data structure for quickly dealing with nested data in different formats
Home-page: https://github.com/QuinnFreedman/QueryTree
Author: Quinn Freedman
Author-email: quinnfreedman@gmail.com
License: UNKNOWN
Platform: UNKNOWN
Classifier: Programming Language :: Python :: 3
Classifier: License :: OSI Approved :: MIT License
Classifier: Operating System :: OS Independent
Requires-Python: >=3.6
